{
  "data_path": "C:\\Users\\Admin\\Desktop\\hhh\\Horse\\data_preprocessing\\merged_data_kr_Nan.csv",
  "rows": 15460,
  "columns": 28,
  "history_feature_count": 30,
  "split_rows": {
    "train": 12111,
    "valid": 1587,
    "test": 1762
  },
  "split_rule": {
    "train_before": "2026-01-01",
    "validation_period": "2026 first half of race dates",
    "test_period": "2026 second half of race dates"
  },
  "feature_notes": {
    "target": "순위점수",
    "rank_reference": "순위",
    "dropped_for_leakage": [
      "경주기록",
      "순위",
      "순위점수"
    ],
    "date_features_added": [
      "age_days",
      "age_years",
      "race_year",
      "race_month",
      "race_weekday"
    ],
    "history_entities": [
      "마명",
      "기수번호",
      "조교사번호"
    ],
    "history_examples": [
      "horse_prev_score_mean",
      "horse_prev_win_rate",
      "jockey_last_rank",
      "trainer_prev_top3_rate"
    ]
  },
  "validation_metrics": {
    "ridge_baseline_history": {
      "model": "ridge_baseline_history",
      "mae": 0.2513405516550056,
      "rmse": 0.29900847189833546,
      "r2": 0.08213889251074014,
      "winner_accuracy": 0.25301204819277107,
      "winner_in_top_3_rate": 0.5903614457831325,
      "ndcg_at_3": 0.7197376167402941
    },
    "best_lightgbm_history": {
      "model": "lightgbm_candidate_3",
      "mae": 0.2438340786715577,
      "rmse": 0.29047521774321555,
      "r2": 0.13378010789920558,
      "winner_accuracy": 0.3253012048192771,
      "winner_in_top_3_rate": 0.6385542168674698,
      "ndcg_at_3": 0.7390624170745326,
      "params": {
        "n_estimators": 700,
        "learning_rate": 0.03,
        "num_leaves": 63,
        "min_child_samples": 25,
        "subsample": 0.8,
        "colsample_bytree": 0.8,
        "reg_alpha": 0.2,
        "reg_lambda": 0.3
      }
    }
  },
  "selected_lightgbm_params": {
    "n_estimators": 700,
    "learning_rate": 0.03,
    "num_leaves": 63,
    "min_child_samples": 25,
    "subsample": 0.8,
    "colsample_bytree": 0.8,
    "reg_alpha": 0.2,
    "reg_lambda": 0.3
  },
  "test_metrics": {
    "model": "lightgbm_history_final",
    "mae": 0.23919235313907397,
    "rmse": 0.2863600433172997,
    "r2": 0.16616650658741594,
    "winner_accuracy": 0.23121387283236994,
    "winner_in_top_3_rate": 0.5895953757225434,
    "ndcg_at_3": 0.7571953217671716
  },
  "top_10_feature_importance": [
    {
      "feature": "num__jockey_prev_weight_mean",
      "importance": 1713
    },
    {
      "feature": "num__age_days",
      "importance": 1680
    },
    {
      "feature": "num__마체중",
      "importance": 1545
    },
    {
      "feature": "num__trainer_prev_weight_mean",
      "importance": 1532
    },
    {
      "feature": "num__horse_prev_weight_mean",
      "importance": 1376
    },
    {
      "feature": "num__마번",
      "importance": 1363
    },
    {
      "feature": "num__jockey_prev_win_rate",
      "importance": 1282
    },
    {
      "feature": "num__trainer_prev_win_rate",
      "importance": 1275
    },
    {
      "feature": "num__trainer_prev_count",
      "importance": 1268
    },
    {
      "feature": "num__horse_prev_score_mean",
      "importance": 1258
    }
  ],
  "artifacts": {
    "model": "C:\\Users\\Admin\\Desktop\\hhh\\Horse\\src\\hw\\rank_model_history_lightgbm.joblib",
    "predictions": "C:\\Users\\Admin\\Desktop\\hhh\\Horse\\src\\hw\\rank_model_history_test_predictions.csv",
    "feature_importance": "C:\\Users\\Admin\\Desktop\\hhh\\Horse\\src\\hw\\rank_model_history_feature_importance.csv",
    "results": "C:\\Users\\Admin\\Desktop\\hhh\\Horse\\src\\hw\\rank_model_history_results.json"
  }
}